{
  "id": 17907993141,
  "name": "PUSH_30032026",
  "type": "WeightTraining",
  "sport_type": "WeightTraining",
  "start_date": "2026-03-30T02:07:36Z",
  "start_date_local": "2026-03-30T07:37:36Z",
  "start_date_unix": 1774836456,
  "description": "Logged with Hevy\r\n\r\nBench Press (Dumbbell)\r\nSet 1: 15 kg x 20 \r\nSet 2: 15 kg x 20 \r\nSet 3: 15 kg x 20 \r\n\r\nIncline Bench Press (Dumbbell)\r\nSet 1: 15 kg x 20 \r\nSet 2: 15 kg x 20 \r\nSet 3: 15 kg x 20 \r\n\r\nShoulder Press (Dumbbell)\r\nSet 1: 15 kg x 20 \r\nSet 2: 15 kg x 20 \r\nSet 3: 15 kg x 20 \r\n\r\nLateral Raise (Dumbbell)\r\nSet 1: 15 kg x 10 \r\nSet 2: 15 kg x 10 \r\nSet 3: 15 kg x 10 \r\n\r\nTriceps Extension (Dumbbell)\r\nSet 1: 7.5 kg x 20 \r\nSet 2: 7.5 kg x 20 \r\nSet 3: 7.5 kg x 20 \r\n\r\nPush Up\r\nSet 1: 20 reps \r\nSet 2: 20 reps \r\n",
  "timezone": "(GMT+05:30) Asia/Kolkata",
  "start_latlng": [],
  "end_latlng": [],
  "location_city": null,
  "location_state": null,
  "location_country": null,
  "distance_m": 0.0,
  "moving_time_s": 1873,
  "elapsed_time_s": 1873,
  "total_elevation_m": 0.0,
  "average_heartrate": null,
  "max_heartrate": null,
  "average_watts": null,
  "kilojoules": null,
  "average_speed_ms": 0.0,
  "max_speed_ms": 0,
  "calories": 0,
  "suffer_score": null,
  "trainer": false,
  "commute": false,
  "manual": true,
  "gear_id": null
}